airtest_manager/__init__.py
airtest_manager/template_manager.py
airtest_manager-0.0.2.dist-info/LICENSE
airtest_manager-0.0.2.dist-info/METADATA
airtest_manager-0.0.2.dist-info/WHEEL
airtest_manager-0.0.2.dist-info/top_level.txt
airtest_manager-0.0.2.dist-info/RECORD
