Metadata-Version: 2.1
Name: airtest-manager
Version: 0.0.2
Summary: support using image url for airtest Template
Home-page: https://github.com/nibilin33/airtest_manager
Author: nibilin33
Author-email: nibilin33@gmail.com
Classifier: Programming Language :: Python :: 3
Classifier: License :: OSI Approved :: MIT License
Classifier: Operating System :: OS Independent
Requires-Python: >=3.6
License-File: LICENSE
Requires-Dist: requests
Requires-Dist: airtest
